test_day/__init__.py
test_day-0.1.0.dist-info/WHEEL
test_day-0.1.0.dist-info/METADATA
test_day-0.1.0.dist-info/RECORD
