Metadata-Version: 2.1
Name: test-day
Version: 0.1.0
Summary: 
Author: Stefan Hagemann
Author-email: StefanHagemann@gmx.at
Requires-Python: >=3.9,<4.0
Classifier: Programming Language :: Python :: 3
Classifier: Programming Language :: Python :: 3.10
Classifier: Programming Language :: Python :: 3.9
Requires-Dist: matplotlib (>=3.5.2,<4.0.0)
Requires-Dist: pandas (>=1.4.3,<2.0.0)
